catsordogs/__init__.py
catsordogs/__main__.py
catsordogs/classify.py
catsordogs/logfatal.py
catsordogs/model.h5
catsordogs/pickimage.py
catsordogs/preprocess.py
catsordogs/test1.jpeg
catsordogs/test2.jpeg
catsordogs-0.0.9.dist-info/METADATA
catsordogs-0.0.9.dist-info/WHEEL
catsordogs-0.0.9.dist-info/entry_points.txt
catsordogs-0.0.9.dist-info/licenses/LICENSE
catsordogs-0.0.9.dist-info/RECORD
